click_configfile.py
click_configfile-0.2.3.dist-info/DESCRIPTION.rst
click_configfile-0.2.3.dist-info/METADATA
click_configfile-0.2.3.dist-info/RECORD
click_configfile-0.2.3.dist-info/WHEEL
click_configfile-0.2.3.dist-info/metadata.json
click_configfile-0.2.3.dist-info/top_level.txt
click_configfile-0.2.3.dist-info/zip-safe
