Metadata-Version: 1.1
Name: click-configfile
Version: 0.2.3
Summary: This package supports click commands that use configuration files.
Home-page: https://github.com/click-contrib/click-configfile
Author: Jens Engel
Author-email: jenisys@noreply.github.com
License: BSD
Download-URL: https://pypi.python.org/pypi/click-configfile/0.2.3
Keywords: click,configfile,configparser
Platform: any
Classifier: License :: OSI Approved :: BSD License
Classifier: Development Status :: 3 - Alpha
Classifier: Environment :: Console
Classifier: Intended Audience :: Developers
Classifier: Intended Audience :: End Users/Desktop
Classifier: Intended Audience :: System Administrators
Classifier: Natural Language :: English
Classifier: Programming Language :: Python
Classifier: Programming Language :: Python :: 2
Classifier: Programming Language :: Python :: 2.6
Classifier: Programming Language :: Python :: 2.7
Classifier: Programming Language :: Python :: 3
Classifier: Topic :: Utilities
